src/.gitignore
src/__init__.py
src/config.py
src/main.py
src/models.py
src/routes.py
src/schemas.py
src/static/css/style.css
src/static/js/script.js
src/templates/base.html
src/templates/index.html
src/tests/__init__.py
src/tests/test_main.py
src/tests/test_routes.py
study_flashcard-0.1.0.dist-info/LICENSE
study_flashcard-0.1.0.dist-info/METADATA
study_flashcard-0.1.0.dist-info/WHEEL
study_flashcard-0.1.0.dist-info/RECORD
