Metadata-Version: 2.1
Name: study-flashcard
Version: 0.1.0
Summary: 
License: GPL-3.0
Author: Thuc Phan
Author-email: kienthuc.phan@gmail.com
Requires-Python: >=3.8.1,<4.0.0
Classifier: License :: OSI Approved :: GNU General Public License v3 (GPLv3)
Classifier: Programming Language :: Python :: 3
Classifier: Programming Language :: Python :: 3.9
Classifier: Programming Language :: Python :: 3.10
Classifier: Programming Language :: Python :: 3.11
Requires-Dist: coverage (==7.2.1)
Requires-Dist: dnspython (==2.3.0)
Requires-Dist: fastapi (==0.92.0)
Requires-Dist: flake8 (==6.0.0)
Requires-Dist: html5lib (==1.1)
Requires-Dist: httpx (==0.23.3)
Requires-Dist: jinja2 (==3.1.2)
Requires-Dist: mongoengine (==0.26.0)
Requires-Dist: poetry (==1.3.2)
Requires-Dist: pydantic (==1.10.5)
Requires-Dist: pymongo (==4.2.0)
Requires-Dist: pytest-cov (==4.0.0)
Requires-Dist: pytest-dotenv (==0.5.2)
Requires-Dist: python-dotenv (==1.0.0)
Requires-Dist: python-semantic-release (==7.33.2)
Requires-Dist: starlette (==0.25.0)
Requires-Dist: uvicorn (==0.20.0)
